README.md
setup.py
tfpred/__init__.py
tfpred.egg-info/PKG-INFO
tfpred.egg-info/SOURCES.txt
tfpred.egg-info/dependency_links.txt
tfpred.egg-info/top_level.txt